wham/__init__.py
wham/plot.py
wham/wham.py
wham-0.1.1.dist-info/LICENSE
wham-0.1.1.dist-info/METADATA
wham-0.1.1.dist-info/WHEEL
wham-0.1.1.dist-info/top_level.txt
wham-0.1.1.dist-info/RECORD
